pyworkout/__init__.py
pyworkout/parsers/__init__.py
pyworkout/parsers/base.py
pyworkout/parsers/tcxtools.py
pyworkout/tests/__init__.py
pyworkout/tests/test_basic.py
pyworkout_toolkit-0.0.1.dist-info/DESCRIPTION.rst
pyworkout_toolkit-0.0.1.dist-info/METADATA
pyworkout_toolkit-0.0.1.dist-info/RECORD
pyworkout_toolkit-0.0.1.dist-info/WHEEL
pyworkout_toolkit-0.0.1.dist-info/metadata.json
pyworkout_toolkit-0.0.1.dist-info/top_level.txt
