Metadata-Version: 2.0
Name: pyworkout-toolkit
Version: 0.0.1
Summary: Python tools to process workout data and telemetry
Home-page: https://github.com/triskadecaepyon/pyworkout-toolkit/
Author: David Liu
Author-email: dcltechnology@gmail.com
License: BSD
Keywords: workout data telemetry
Platform: UNKNOWN
Classifier: Development Status :: 3 - Alpha
Classifier: Intended Audience :: Developers
Classifier: Topic :: Scientific/Engineering
Classifier: License :: OSI Approved :: BSD License
Classifier: Programming Language :: Python
Classifier: Operating System :: Microsoft :: Windows
Classifier: Operating System :: POSIX
Classifier: Operating System :: Unix
Classifier: Operating System :: MacOS
Classifier: Programming Language :: Python :: 3
Classifier: Programming Language :: Python :: 3.4
Classifier: Programming Language :: Python :: 3.5
Requires-Dist: lxml
Requires-Dist: numpy
Requires-Dist: pandas
